<odoo>
    <data>
        <record model="ir.ui.view" id="hr_employee_form_inherit">
            <field name="name">hr.employee.form.inherit</field>
            <field name="model">hr.employee</field>
            <field name="inherit_id" ref="hr.view_employee_form"/>
            <field name="arch" type="xml">
            <field name="work_location_id" position="after">
                <tr>
                    <td colspan="2" style="width: 100%;">
                        <div class="o_horizontal_separator">Goals</div>
                    </td>
                </tr>
                    <field name="company_goal"/>
                    <field name="employee_goal"/> 
                    </field>
             </field> 
         </record>
    </data>
</odoo>